{
    "ETag": "E3P5ROKL5A1OLE",
    "DistributionConfig": {
        "CallerReference": "grace2-cf-20260613-01",
        "Aliases": {
            "Quantity": 0
        },
        "DefaultRootObject": "index.html",
        "Origins": {
            "Quantity": 5,
            "Items": [
                {
                    "Id": "origin-agent-ws",
                    "DomainName": "ec2-54-185-114-233.us-west-2.compute.amazonaws.com",
                    "OriginPath": "",
                    "CustomHeaders": {
                        "Quantity": 0
                    },
                    "CustomOriginConfig": {
                        "HTTPPort": 8765,
                        "HTTPSPort": 443,
                        "OriginProtocolPolicy": "http-only",
                        "OriginSslProtocols": {
                            "Quantity": 1,
                            "Items": [
                                "TLSv1.2"
                            ]
                        },
                        "OriginReadTimeout": 60,
                        "OriginKeepaliveTimeout": 60
                    },
                    "ConnectionAttempts": 3,
                    "ConnectionTimeout": 10,
                    "OriginShield": {
                        "Enabled": false
                    },
                    "OriginAccessControlId": ""
                },
                {
                    "Id": "origin-titiler",
                    "DomainName": "ec2-44-247-187-124.us-west-2.compute.amazonaws.com",
                    "OriginPath": "",
                    "CustomHeaders": {
                        "Quantity": 0
                    },
                    "CustomOriginConfig": {
                        "HTTPPort": 8080,
                        "HTTPSPort": 443,
                        "OriginProtocolPolicy": "http-only",
                        "OriginSslProtocols": {
                            "Quantity": 1,
                            "Items": [
                                "TLSv1.2"
                            ]
                        },
                        "OriginReadTimeout": 30,
                        "OriginKeepaliveTimeout": 5
                    },
                    "ConnectionAttempts": 3,
                    "ConnectionTimeout": 10,
                    "OriginShield": {
                        "Enabled": false
                    },
                    "OriginAccessControlId": ""
                },
                {
                    "Id": "origin-s3-web",
                    "DomainName": "grace2-hazard-web-226996537797.s3-website-us-west-2.amazonaws.com",
                    "OriginPath": "",
                    "CustomHeaders": {
                        "Quantity": 0
                    },
                    "CustomOriginConfig": {
                        "HTTPPort": 80,
                        "HTTPSPort": 443,
                        "OriginProtocolPolicy": "http-only",
                        "OriginSslProtocols": {
                            "Quantity": 1,
                            "Items": [
                                "TLSv1.2"
                            ]
                        },
                        "OriginReadTimeout": 30,
                        "OriginKeepaliveTimeout": 5
                    },
                    "ConnectionAttempts": 3,
                    "ConnectionTimeout": 10,
                    "OriginShield": {
                        "Enabled": false
                    },
                    "OriginAccessControlId": ""
                },
                {
                    "Id": "origin-catalog",
                    "DomainName": "ec2-54-185-114-233.us-west-2.compute.amazonaws.com",
                    "OriginPath": "",
                    "CustomHeaders": {
                        "Quantity": 0
                    },
                    "CustomOriginConfig": {
                        "HTTPPort": 8766,
                        "HTTPSPort": 443,
                        "OriginProtocolPolicy": "http-only",
                        "OriginSslProtocols": {
                            "Quantity": 1,
                            "Items": [
                                "TLSv1.2"
                            ]
                        },
                        "OriginReadTimeout": 30,
                        "OriginKeepaliveTimeout": 5
                    },
                    "ConnectionAttempts": 3,
                    "ConnectionTimeout": 10,
                    "OriginShield": {
                        "Enabled": false
                    },
                    "OriginAccessControlId": ""
                },
                {
                    "Id": "origin-broker-ws",
                    "DomainName": "grace2-agent-broker-872872610.us-west-2.elb.amazonaws.com",
                    "OriginPath": "",
                    "CustomHeaders": {
                        "Quantity": 0
                    },
                    "CustomOriginConfig": {
                        "HTTPPort": 80,
                        "HTTPSPort": 443,
                        "OriginProtocolPolicy": "http-only",
                        "OriginSslProtocols": {
                            "Quantity": 1,
                            "Items": [
                                "TLSv1.2"
                            ]
                        },
                        "OriginReadTimeout": 60,
                        "OriginKeepaliveTimeout": 60
                    },
                    "ConnectionAttempts": 3,
                    "ConnectionTimeout": 10,
                    "OriginShield": {
                        "Enabled": false
                    },
                    "OriginAccessControlId": ""
                }
            ]
        },
        "OriginGroups": {
            "Quantity": 0
        },
        "DefaultCacheBehavior": {
            "TargetOriginId": "origin-s3-web",
            "TrustedSigners": {
                "Enabled": false,
                "Quantity": 0
            },
            "TrustedKeyGroups": {
                "Enabled": false,
                "Quantity": 0
            },
            "ViewerProtocolPolicy": "redirect-to-https",
            "AllowedMethods": {
                "Quantity": 2,
                "Items": [
                    "HEAD",
                    "GET"
                ],
                "CachedMethods": {
                    "Quantity": 2,
                    "Items": [
                        "HEAD",
                        "GET"
                    ]
                }
            },
            "SmoothStreaming": false,
            "Compress": true,
            "LambdaFunctionAssociations": {
                "Quantity": 0
            },
            "FunctionAssociations": {
                "Quantity": 0
            },
            "FieldLevelEncryptionId": "",
            "CachePolicyId": "658327ea-f89d-4fab-a63d-7e88639e58f6",
            "GrpcConfig": {
                "Enabled": false
            }
        },
        "CacheBehaviors": {
            "Quantity": 4,
            "Items": [
                {
                    "PathPattern": "/ws*",
                    "TargetOriginId": "origin-broker-ws",
                    "TrustedSigners": {
                        "Enabled": false,
                        "Quantity": 0
                    },
                    "TrustedKeyGroups": {
                        "Enabled": false,
                        "Quantity": 0
                    },
                    "ViewerProtocolPolicy": "redirect-to-https",
                    "AllowedMethods": {
                        "Quantity": 7,
                        "Items": [
                            "HEAD",
                            "DELETE",
                            "POST",
                            "GET",
                            "OPTIONS",
                            "PUT",
                            "PATCH"
                        ],
                        "CachedMethods": {
                            "Quantity": 2,
                            "Items": [
                                "HEAD",
                                "GET"
                            ]
                        }
                    },
                    "SmoothStreaming": false,
                    "Compress": false,
                    "LambdaFunctionAssociations": {
                        "Quantity": 0
                    },
                    "FunctionAssociations": {
                        "Quantity": 0
                    },
                    "FieldLevelEncryptionId": "",
                    "CachePolicyId": "4135ea2d-6df8-44a3-9df3-4b5a84be39ad",
                    "OriginRequestPolicyId": "216adef6-5c7f-47e4-b989-5492eafa07d3",
                    "GrpcConfig": {
                        "Enabled": false
                    }
                },
                {
                    "PathPattern": "/cog/*",
                    "TargetOriginId": "origin-titiler",
                    "TrustedSigners": {
                        "Enabled": false,
                        "Quantity": 0
                    },
                    "TrustedKeyGroups": {
                        "Enabled": false,
                        "Quantity": 0
                    },
                    "ViewerProtocolPolicy": "redirect-to-https",
                    "AllowedMethods": {
                        "Quantity": 3,
                        "Items": [
                            "HEAD",
                            "GET",
                            "OPTIONS"
                        ],
                        "CachedMethods": {
                            "Quantity": 2,
                            "Items": [
                                "HEAD",
                                "GET"
                            ]
                        }
                    },
                    "SmoothStreaming": false,
                    "Compress": true,
                    "LambdaFunctionAssociations": {
                        "Quantity": 0
                    },
                    "FunctionAssociations": {
                        "Quantity": 0
                    },
                    "FieldLevelEncryptionId": "",
                    "CachePolicyId": "3d3fdb28-3073-4a8e-bb60-9f8b4de7e972",
                    "ResponseHeadersPolicyId": "75430207-2c36-459a-aefe-b794438ee7c7",
                    "GrpcConfig": {
                        "Enabled": false
                    }
                },
                {
                    "PathPattern": "/tiles*",
                    "TargetOriginId": "origin-titiler",
                    "TrustedSigners": {
                        "Enabled": false,
                        "Quantity": 0
                    },
                    "TrustedKeyGroups": {
                        "Enabled": false,
                        "Quantity": 0
                    },
                    "ViewerProtocolPolicy": "redirect-to-https",
                    "AllowedMethods": {
                        "Quantity": 3,
                        "Items": [
                            "HEAD",
                            "GET",
                            "OPTIONS"
                        ],
                        "CachedMethods": {
                            "Quantity": 2,
                            "Items": [
                                "HEAD",
                                "GET"
                            ]
                        }
                    },
                    "SmoothStreaming": false,
                    "Compress": true,
                    "LambdaFunctionAssociations": {
                        "Quantity": 0
                    },
                    "FunctionAssociations": {
                        "Quantity": 0
                    },
                    "FieldLevelEncryptionId": "",
                    "CachePolicyId": "3d3fdb28-3073-4a8e-bb60-9f8b4de7e972",
                    "ResponseHeadersPolicyId": "75430207-2c36-459a-aefe-b794438ee7c7",
                    "GrpcConfig": {
                        "Enabled": false
                    }
                },
                {
                    "PathPattern": "/api/*",
                    "TargetOriginId": "origin-catalog",
                    "TrustedSigners": {
                        "Enabled": false,
                        "Quantity": 0
                    },
                    "TrustedKeyGroups": {
                        "Enabled": false,
                        "Quantity": 0
                    },
                    "ViewerProtocolPolicy": "redirect-to-https",
                    "AllowedMethods": {
                        "Quantity": 3,
                        "Items": [
                            "HEAD",
                            "GET",
                            "OPTIONS"
                        ],
                        "CachedMethods": {
                            "Quantity": 2,
                            "Items": [
                                "HEAD",
                                "GET"
                            ]
                        }
                    },
                    "SmoothStreaming": false,
                    "Compress": true,
                    "LambdaFunctionAssociations": {
                        "Quantity": 0
                    },
                    "FunctionAssociations": {
                        "Quantity": 0
                    },
                    "FieldLevelEncryptionId": "",
                    "CachePolicyId": "4135ea2d-6df8-44a3-9df3-4b5a84be39ad",
                    "OriginRequestPolicyId": "216adef6-5c7f-47e4-b989-5492eafa07d3",
                    "ResponseHeadersPolicyId": "75430207-2c36-459a-aefe-b794438ee7c7",
                    "GrpcConfig": {
                        "Enabled": false
                    }
                }
            ]
        },
        "CustomErrorResponses": {
            "Quantity": 2,
            "Items": [
                {
                    "ErrorCode": 403,
                    "ResponsePagePath": "/index.html",
                    "ResponseCode": "200",
                    "ErrorCachingMinTTL": 10
                },
                {
                    "ErrorCode": 404,
                    "ResponsePagePath": "/index.html",
                    "ResponseCode": "200",
                    "ErrorCachingMinTTL": 10
                }
            ]
        },
        "Comment": "GRACE-2 HTTPS/WSS edge: S3 web + EC2 agent(8765)/titiler(8080)/catalog(8766)",
        "Logging": {
            "Enabled": false,
            "IncludeCookies": false,
            "Bucket": "",
            "Prefix": ""
        },
        "PriceClass": "PriceClass_100",
        "Enabled": true,
        "ViewerCertificate": {
            "CloudFrontDefaultCertificate": true,
            "SSLSupportMethod": "vip",
            "MinimumProtocolVersion": "TLSv1",
            "CertificateSource": "cloudfront"
        },
        "Restrictions": {
            "GeoRestriction": {
                "RestrictionType": "none",
                "Quantity": 0
            }
        },
        "WebACLId": "",
        "HttpVersion": "http2",
        "IsIPV6Enabled": true,
        "ContinuousDeploymentPolicyId": "",
        "Staging": false
    }
}
